{"stats":{"minecraft:mined":{"minecraft:short_grass":1},"minecraft:custom":{"minecraft:jump":190,"minecraft:time_since_rest":29608,"minecraft:damage_dealt":110,"minecraft:crouch_one_cm":292,"minecraft:leave_game":3,"minecraft:sprint_one_cm":15533,"minecraft:play_time":29608,"minecraft:damage_taken":60,"minecraft:time_since_death":29608,"minecraft:walk_one_cm":10125,"minecraft:sneak_time":142,"minecraft:total_world_time":29608,"minecraft:fall_one_cm":7971,"minecraft:fly_one_cm":53362},"minecraft:used":{"minecraft:chicken":1}},"DataVersion":3953}